complatecpp/core.cp37-win_amd64.pyd
complatecpp/quickjs.cp37-win_amd64.pyd
complatecpp/__init__.py
complatecpp/lib/cmake/complate-cpp-for-python/complate-cpp-for-python-config-version.cmake
complatecpp/lib/cmake/complate-cpp-for-python/complate-cpp-for-python-config.cmake
complatecpp/lib/cmake/complate-cpp-for-python/complate-cpp-for-python-targets-release.cmake
complatecpp/lib/cmake/complate-cpp-for-python/complate-cpp-for-python-targets.cmake
complate_cpp_for_python-0.0.2.data/data/.release-it.json
complate_cpp_for_python-0.0.2.data/data/CHANGELOG.md
complate_cpp_for_python-0.0.2.data/data/CMakeLists.txt
complate_cpp_for_python-0.0.2.data/data/faucet.config.js
complate_cpp_for_python-0.0.2.data/data/LICENSE
complate_cpp_for_python-0.0.2.data/data/MANIFEST.in
complate_cpp_for_python-0.0.2.data/data/package-lock.json
complate_cpp_for_python-0.0.2.data/data/package.json
complate_cpp_for_python-0.0.2.data/data/pyproject.toml
complate_cpp_for_python-0.0.2.data/data/README.md
complate_cpp_for_python-0.0.2.data/data/requirements.txt
complate_cpp_for_python-0.0.2.data/data/setup.py
complate_cpp_for_python-0.0.2.data/data/USER_GUIDE.md
complate_cpp_for_python-0.0.2.data/data/VERSION
complate_cpp_for_python-0.0.2.data/data/cmake/Complate.cmake
complate_cpp_for_python-0.0.2.data/data/cmake/PyBind11.cmake
complate_cpp_for_python-0.0.2.data/data/src/complate_cpp_for_python.egg-info/dependency_links.txt
complate_cpp_for_python-0.0.2.data/data/src/complate_cpp_for_python.egg-info/requires.txt
complate_cpp_for_python-0.0.2.data/data/src/complate_cpp_for_python.egg-info/SOURCES.txt
complate_cpp_for_python-0.0.2.data/data/src/complate_cpp_for_python.egg-info/top_level.txt
complate_cpp_for_python-0.0.2.data/data/src/core/CMakeLists.txt
complate_cpp_for_python-0.0.2.data/data/src/core/core.cpp
complate_cpp_for_python-0.0.2.data/data/src/core/function.h
complate_cpp_for_python-0.0.2.data/data/src/core/renderer.h
complate_cpp_for_python-0.0.2.data/data/src/core/stream.h
complate_cpp_for_python-0.0.2.data/data/src/core/stringstream.h
complate_cpp_for_python-0.0.2.data/data/src/core/value.h
complate_cpp_for_python-0.0.2.data/data/src/quickjs/CMakeLists.txt
complate_cpp_for_python-0.0.2.data/data/src/quickjs/prototypes.cpp
complate_cpp_for_python-0.0.2.data/data/src/quickjs/prototypes.h
complate_cpp_for_python-0.0.2.dist-info/DELVEWHEEL
complate_cpp_for_python-0.0.2.dist-info/LICENSE
complate_cpp_for_python-0.0.2.dist-info/METADATA
complate_cpp_for_python-0.0.2.dist-info/RECORD
complate_cpp_for_python-0.0.2.dist-info/top_level.txt
complate_cpp_for_python-0.0.2.dist-info/WHEEL
