Metadata-Version: 2.1
Name: complate-cpp-for-python
Version: 0.0.2
Summary: Rendering of JSX based views in Python
Home-page: https://github.com/tmehnert/complate-cpp-for-python
Author: Torsten Mehnert
Author-email: torsten.mhn@gmail.com
License: Apache-2.0
Project-URL: Documentation, https://github.com/tmehnert/complate-cpp-for-python/blob/main/USER_GUIDE.md
Project-URL: Source Code, https://github.com/tmehnert/complate-cpp-for-python
Project-URL: Bug Tracker, https://github.com/tmehnert/complate-cpp-for-python/issues
Project-URL: Changelog, https://github.com/tmehnert/complate-cpp-for-python/blob/main/CHANGELOG.md
Keywords: jsx,html,template-engine
Platform: UNKNOWN
Classifier: License :: OSI Approved :: Apache Software License
Classifier: Operating System :: POSIX :: Linux
Classifier: Operating System :: Microsoft :: Windows
Classifier: Operating System :: MacOS :: MacOS X
Classifier: Programming Language :: Python
Classifier: Programming Language :: C++
Classifier: Programming Language :: C
Classifier: Environment :: Web Environment
Classifier: Topic :: Internet :: WWW/HTTP :: Dynamic Content
Classifier: Topic :: Text Processing :: Markup :: HTML
Requires-Python: >=3.6
Provides-Extra: test
License-File: LICENSE
